fiberpath/__init__.py
fiberpath/math_utils.py
fiberpath/config/__init__.py
fiberpath/config/schemas.py
fiberpath/config/validator.py
fiberpath/execution/__init__.py
fiberpath/execution/marlin.py
fiberpath/gcode/__init__.py
fiberpath/gcode/dialects.py
fiberpath/gcode/generator.py
fiberpath/geometry/__init__.py
fiberpath/geometry/curves.py
fiberpath/geometry/intersections.py
fiberpath/geometry/surfaces.py
fiberpath/planning/__init__.py
fiberpath/planning/calculations.py
fiberpath/planning/exceptions.py
fiberpath/planning/helpers.py
fiberpath/planning/layer_strategies.py
fiberpath/planning/machine.py
fiberpath/planning/planner.py
fiberpath/planning/validators.py
fiberpath/simulation/__init__.py
fiberpath/simulation/simulator.py
fiberpath/visualization/__init__.py
fiberpath/visualization/export_json.py
fiberpath/visualization/plotter.py
fiberpath_api/__init__.py
fiberpath_api/main.py
fiberpath_api/package-lock.json
fiberpath_api/schemas.py
fiberpath_api/routes/__init__.py
fiberpath_api/routes/plan.py
fiberpath_api/routes/simulate.py
fiberpath_api/routes/stream.py
fiberpath_api/routes/validate.py
fiberpath_cli/__init__.py
fiberpath_cli/__main__.py
fiberpath_cli/interactive.py
fiberpath_cli/main.py
fiberpath_cli/output.py
fiberpath_cli/plan.py
fiberpath_cli/plot.py
fiberpath_cli/simulate.py
fiberpath_cli/stream.py
fiberpath_cli/validate.py
fiberpath-0.5.1.dist-info/METADATA
fiberpath-0.5.1.dist-info/WHEEL
fiberpath-0.5.1.dist-info/entry_points.txt
fiberpath-0.5.1.dist-info/licenses/LICENSE
fiberpath-0.5.1.dist-info/RECORD
