Metadata-Version: 2.4
Name: fiberpath
Version: 0.5.1
Summary: Modern filament winding planner, simulator, and G-code toolkit.
Author: Cameron K. Brooks
License:                     GNU AFFERO GENERAL PUBLIC LICENSE
License-File: LICENSE
Keywords: cnc,composites,filament-winding,gcode
Classifier: License :: OSI Approved :: GNU Affero General Public License v3
Classifier: Operating System :: OS Independent
Classifier: Programming Language :: Python :: 3
Classifier: Programming Language :: Python :: 3.11
Classifier: Programming Language :: Python :: 3.12
Requires-Python: >=3.11
Requires-Dist: numpy>=1.26
Requires-Dist: pillow>=10.3
Requires-Dist: pydantic>=2.7
Requires-Dist: pyserial>=3.5
Requires-Dist: rich>=13.7
Requires-Dist: typer>=0.12
Provides-Extra: api
Requires-Dist: fastapi>=0.110; extra == 'api'
Requires-Dist: uvicorn[standard]>=0.24; extra == 'api'
Provides-Extra: cli
Requires-Dist: rich>=13.7; extra == 'cli'
Requires-Dist: typer>=0.12; extra == 'cli'
Provides-Extra: dev
Requires-Dist: httpx>=0.27; extra == 'dev'
Requires-Dist: mypy>=1.10; extra == 'dev'
Requires-Dist: pre-commit>=3.7; extra == 'dev'
Requires-Dist: pyinstaller>=6.0; extra == 'dev'
Requires-Dist: pytest-cov>=4.1; extra == 'dev'
Requires-Dist: pytest>=8.2; extra == 'dev'
Requires-Dist: ruff>=0.7; extra == 'dev'
Requires-Dist: types-pyserial>=3.5; extra == 'dev'
Provides-Extra: docs
Requires-Dist: mkdocs-material>=9.5; extra == 'docs'
Requires-Dist: mkdocs>=1.5; extra == 'docs'
Requires-Dist: pymdown-extensions>=10.0; extra == 'docs'
Provides-Extra: plot
Requires-Dist: matplotlib>=3.8; extra == 'plot'
Requires-Dist: plotly>=5.22; extra == 'plot'
